InvertedIndexFreq.py
InvertedIndexFreq-0.8.dist-info/METADATA
InvertedIndexFreq-0.8.dist-info/WHEEL
InvertedIndexFreq-0.8.dist-info/top_level.txt
InvertedIndexFreq-0.8.dist-info/RECORD
